{
  "include": [
    ".env.example",
    ".gitignore",
    "README.md",
    "package.json",
    "package-lock.json",
    "eslint.config.js",
    "stylelint.config.js",
    "playwright.config.js",
    "apps",
    "services",
    "external",
    "libs",
    "e2e",
    "scripts",
    "docs/reports/submission",
    "sandbox-repo"
  ],
  "runIds": [
    "run-2026-05-21T02-16-15-215Z",
    "run-2026-05-21T05-51-56-519Z",
    "run-2026-05-21T05-52-12-490Z",
    "run-2026-05-21T05-52-18-277Z",
    "run-2026-05-21T05-58-01-181Z",
    "run-2026-05-21T06-21-56-710Z",
    "run-2026-05-21T06-24-47-248Z"
  ],
  "required": [
    "README.md",
    "package.json",
    "package-lock.json",
    ".env.example",
    "apps/api/src/app.js",
    "apps/api/src/apiErrors.js",
    "apps/api/src/continueWorkflow.js",
    "apps/api/src/runEvidenceRoutes.js",
    "apps/api/src/runEvidenceGuards.js",
    "apps/api/src/runExecutionRoutes.js",
    "apps/api/src/runArchiveReaders.js",
    "apps/api/src/runArchiveNormalize.js",
    "apps/api/src/runRouteHelpers.js",
    "apps/api/src/runRoutes.js",
    "apps/api/src/runReviewRoutes.js",
    "apps/api/src/systemRoutes.js",
    "apps/web/src/App.jsx",
    "apps/web/src/useConsoleController.js",
    "apps/web/src/components/ConsoleShell.jsx",
    "apps/web/src/components/CrossRunAiUsagePanel.jsx",
    "apps/web/src/components/RunResultPanels.jsx",
    "services/orchestrator/src/orchestrator.js",
    "services/orchestrator/src/aiCallRecords.js",
    "services/orchestrator/src/deliveryPipeline.js",
    "services/orchestrator/src/deliveryContext.js",
    "services/orchestrator/src/aiUsageSummary.js",
    "services/agents/src/requirementAgent.js",
    "services/skills/src/registry.js",
    "services/skills/src/popularTagsTopFive.js",
    "services/checks/src/crossStackSync.js",
    "services/index/src/sandboxIndex.js",
    "scripts/pre-submission-check.sh",
    "scripts/archive-dry-run.mjs",
    "scripts/archive-manifest.json",
    "docs/reports/submission/checklist.md",
    "docs/reports/submission/public-repo-guide.md",
    "docs/reports/submission/team-info.md",
    "sandbox-repo/package.json",
    "sandbox-repo/package-lock.json",
    "sandbox-repo/frontend/package.json",
    "sandbox-repo/backend/package.json"
  ],
  "requiredRunFiles": [
    "requirement.md",
    "history-recall.json",
    "plan.md",
    "diff.patch",
    "verification.json",
    "run-summary.json",
    "pr-draft.md",
    "ai-calls.jsonl"
  ],
  "denyPrefixes": [
    "apps/api/docs/reports/",
    "apps/web/dist/",
    "test-results/"
  ],
  "denySegments": [
    ".git",
    "node_modules"
  ]
}
